{
  "agent": "code-implementor",
  "status": "success",
  "summary": "Created admin API endpoints with 10 routes: events CRUD, categories CRUD, Excel import/export, password management",
  "files_changed": [
    "/Users/maksim/git_projects/rksi_shedule_spo/backend/app/api/admin.py",
    "/Users/maksim/git_projects/rksi_shedule_spo/backend/app/services/__init__.py"
  ],
  "files_created": [
    "/Users/maksim/git_projects/rksi_shedule_spo/backend/app/api/admin.py",
    "/Users/maksim/git_projects/rksi_shedule_spo/backend/app/services/excel_import.py",
    "/Users/maksim/git_projects/rksi_shedule_spo/backend/app/services/excel_export.py"
  ],
  "files_deleted": [],
  "tests_status": "skipped",
  "errors": [],
  "warnings": [
    "Excel import/export services are stub implementations - need actual openpyxl logic"
  ],
  "frontend_sync": {
    "required": false,
    "files_updated": []
  },
  "next_steps": [
    "Register admin router in main.py or api/__init__.py",
    "Implement actual Excel import logic in excel_import.py",
    "Implement actual Excel export logic in excel_export.py",
    "Add openpyxl to requirements.txt if not present",
    "Write tests for admin endpoints"
  ],
  "endpoints_created": [
    {
      "method": "GET",
      "path": "/admin/events",
      "description": "Get all events grouped by categories"
    },
    {
      "method": "POST",
      "path": "/admin/events",
      "description": "Create new event"
    },
    {
      "method": "PUT",
      "path": "/admin/events/{event_id}",
      "description": "Update event"
    },
    {
      "method": "DELETE",
      "path": "/admin/events/{event_id}",
      "description": "Delete event with photos"
    },
    {
      "method": "POST",
      "path": "/admin/categories",
      "description": "Create category"
    },
    {
      "method": "DELETE",
      "path": "/admin/categories/{category_id}",
      "description": "Delete category with events"
    },
    {
      "method": "POST",
      "path": "/admin/import",
      "description": "Import from Excel"
    },
    {
      "method": "GET",
      "path": "/admin/export",
      "description": "Export to Excel"
    },
    {
      "method": "PUT",
      "path": "/admin/settings/password",
      "description": "Change public password"
    },
    {
      "method": "PUT",
      "path": "/admin/settings/admin-password",
      "description": "Change admin password"
    }
  ]
}
